tsdae/__init__.py
tsdae/tsdae.py
tsdae-1.1.0.dist-info/LICENSE
tsdae-1.1.0.dist-info/METADATA
tsdae-1.1.0.dist-info/WHEEL
tsdae-1.1.0.dist-info/top_level.txt
tsdae-1.1.0.dist-info/RECORD
