Metadata-Version: 2.1
Name: tsdae
Version: 1.1.0
Summary: Tranformer-based Denoising AutoEncoder for Sentence Transformers Unsupervised pre-training.
Keywords: transformers,sentence-transformers,tsdae,bert,machine-learning,NLP,sentence-similarity,nltk,pre-training,embeddings
Classifier: Programming Language :: Python
Classifier: Programming Language :: Python :: 3
Classifier: Intended Audience :: Education
Classifier: Intended Audience :: Science/Research
Classifier: License :: OSI Approved :: Apache Software License
Classifier: Topic :: Scientific/Engineering
Classifier: Topic :: Scientific/Engineering :: Artificial Intelligence
Classifier: Topic :: Software Development
Classifier: Topic :: Software Development :: Libraries
Classifier: Topic :: Software Development :: Libraries :: Python Modules
License-File: LICENSE
